odoo/addons/project_budget/README.rst
odoo/addons/project_budget/__init__.py
odoo/addons/project_budget/__manifest__.py
odoo/addons/project_budget/i18n/hr.po
odoo/addons/project_budget/i18n/it.po
odoo/addons/project_budget/i18n/project_budget.pot
odoo/addons/project_budget/i18n/sl.po
odoo/addons/project_budget/models/__init__.py
odoo/addons/project_budget/models/account_budget.py
odoo/addons/project_budget/models/project.py
odoo/addons/project_budget/readme/CONTRIBUTORS.rst
odoo/addons/project_budget/readme/DESCRIPTION.rst
odoo/addons/project_budget/readme/USAGE.rst
odoo/addons/project_budget/security/ir.model.access.csv
odoo/addons/project_budget/security/project_security.xml
odoo/addons/project_budget/static/description/icon.png
odoo/addons/project_budget/static/description/index.html
odoo/addons/project_budget/views/account_budget.xml
odoo/addons/project_budget/views/project.xml
odoo12_addon_project_budget-12.0.1.0.0.99.dev13.dist-info/METADATA
odoo12_addon_project_budget-12.0.1.0.0.99.dev13.dist-info/WHEEL
odoo12_addon_project_budget-12.0.1.0.0.99.dev13.dist-info/top_level.txt
odoo12_addon_project_budget-12.0.1.0.0.99.dev13.dist-info/RECORD
