Metadata-Version: 2.1
Name: odoo12-addon-project_budget
Version: 12.0.1.0.0.99.dev13
Summary: Adds budget management to projects.
Home-page: https://github.com/OCA/project
Author: Patrick Wilson,Odoo Community Association (OCA)
Author-email: support@odoo-community.org
License: AGPL-3
Classifier: Programming Language :: Python
Classifier: Framework :: Odoo
Classifier: Framework :: Odoo :: 12.0
Classifier: License :: OSI Approved :: GNU Affero General Public License v3
Classifier: Development Status :: 4 - Beta
Requires-Python: >=3.5
Requires-Dist: odoo12-addon-account-budget-oca
Requires-Dist: odoo<12.1dev,>=12.0a
